labeled_contrastive_framework/__init__.py
labeled_contrastive_framework/module.py
labeled_contrastive_framework/transform.py
labeled_contrastive_framework/utils.py
labeled_contrastive_framework-0.2.13.dist-info/LICENSE
labeled_contrastive_framework-0.2.13.dist-info/METADATA
labeled_contrastive_framework-0.2.13.dist-info/WHEEL
labeled_contrastive_framework-0.2.13.dist-info/top_level.txt
labeled_contrastive_framework-0.2.13.dist-info/RECORD
